telebot_inline_pagination/__init__.py
telebot_inline_pagination-1.2.0.dist-info/LICENSE
telebot_inline_pagination-1.2.0.dist-info/METADATA
telebot_inline_pagination-1.2.0.dist-info/WHEEL
telebot_inline_pagination-1.2.0.dist-info/top_level.txt
telebot_inline_pagination-1.2.0.dist-info/RECORD
