Metadata-Version: 2.1
Name: telebot_inline_pagination
Version: 1.2.0
Summary: Pageable inline keyboard for pyTelegramBotAPI (telebot)
Home-page: https://github.com/kremastra/telebot-inline-pagination
Author: kremastra
Author-email: fotisgrek@gmail.com
Classifier: License :: OSI Approved :: MIT License
License-File: LICENSE
Requires-Dist: telebot
